sclblonnx/__init__.py
sclblonnx/__main__.py
sclblonnx/_globals.py
sclblonnx/constant.py
sclblonnx/input.py
sclblonnx/main.py
sclblonnx/merge.py
sclblonnx/node.py
sclblonnx/output.py
sclblonnx/supported_onnx.json
sclblonnx/utils.py
sclblonnx/validate.py
sclblonnx/version.py
sclblonnx-0.3.0.dist-info/LICENSE
sclblonnx-0.3.0.dist-info/METADATA
sclblonnx-0.3.0.dist-info/WHEEL
sclblonnx-0.3.0.dist-info/top_level.txt
sclblonnx-0.3.0.dist-info/RECORD
