Metadata-Version: 2.1
Name: sclblonnx
Version: 0.3.0
Summary: Python package containing Scailable ONNX tools.
Home-page: https://github.com/scailable/sclblonnx/
Author: Maurits Kaptein
Author-email: maurits.kaptein@scailable.net
Classifier: Programming Language :: Python :: 3
Classifier: License :: OSI Approved :: MIT License
Classifier: Operating System :: OS Independent
Requires-Python: >=3.7
License-File: LICENSE
Requires-Dist: numpy
Requires-Dist: onnxruntime
Requires-Dist: onnx >=1.7.0
Requires-Dist: requests
Requires-Dist: onnxoptimizer
Requires-Dist: onnxsim
Requires-Dist: packaging
